howlongtobeat_scraper/__init__.py
howlongtobeat_scraper/__main__.py
howlongtobeat_scraper/api.py
howlongtobeat_scraper-1.1.3.dist-info/licenses/LICENSE
howlongtobeat_scraper-1.1.3.dist-info/METADATA
howlongtobeat_scraper-1.1.3.dist-info/WHEEL
howlongtobeat_scraper-1.1.3.dist-info/entry_points.txt
howlongtobeat_scraper-1.1.3.dist-info/top_level.txt
howlongtobeat_scraper-1.1.3.dist-info/RECORD
