Metadata-Version: 2.4
Name: howlongtobeat-scraper
Version: 1.1.3
Summary: Un scraper para obtener los tiempos de juego desde HowLongToBeat.com.
Author-email: Sermodi <sermodsoftware@gmail.com>
Project-URL: Homepage, https://github.com/Sermodi/HowLongToBeat_scraper
Project-URL: Bug Tracker, https://github.com/Sermodi/HowLongToBeat_scraper/issues
Project-URL: Repository, https://github.com/Sermodi/HowLongToBeat_scraper
Project-URL: Documentation, https://github.com/Sermodi/HowLongToBeat_scraper#readme
Classifier: Programming Language :: Python :: 3
Classifier: Programming Language :: Python :: 3.8
Classifier: Programming Language :: Python :: 3.9
Classifier: Programming Language :: Python :: 3.10
Classifier: Programming Language :: Python :: 3.11
Classifier: Programming Language :: Python :: 3.12
Classifier: License :: OSI Approved :: MIT License
Classifier: Operating System :: OS Independent
Classifier: Development Status :: 5 - Production/Stable
Classifier: Intended Audience :: Developers
Classifier: Topic :: Games/Entertainment
Classifier: Topic :: Internet :: WWW/HTTP :: Browsers
Classifier: Topic :: Software Development :: Libraries :: Python Modules
Requires-Python: >=3.8
License-File: LICENSE
Requires-Dist: playwright>=1.40.0
Requires-Dist: beautifulsoup4>=4.12.0
Requires-Dist: lxml>=4.9.0
Provides-Extra: dev
Requires-Dist: pytest>=7.4.0; extra == "dev"
Requires-Dist: pytest-cov>=4.1.0; extra == "dev"
Requires-Dist: pytest-asyncio>=0.21.0; extra == "dev"
Requires-Dist: black>=23.0.0; extra == "dev"
Requires-Dist: ruff>=0.1.0; extra == "dev"
Requires-Dist: mypy>=1.5.0; extra == "dev"
Requires-Dist: pre-commit>=3.4.0; extra == "dev"
Requires-Dist: bandit>=1.7.5; extra == "dev"
Provides-Extra: test
Requires-Dist: pytest>=7.4.0; extra == "test"
Requires-Dist: pytest-cov>=4.1.0; extra == "test"
Requires-Dist: pytest-asyncio>=0.21.0; extra == "test"
Dynamic: license-file
